[
    {
    "location": "https://www.cameliahotel.com/wp-content/uploads/2021/11/jennduncan-2_1_.jpeg",
    "taste key": "011100",
    "tags": []
    },
    {
    "location": "https://realfood.tesco.com/media/images/RFO-1400x919-DavidsCurry-03186c71-75ff-4976-bf1f-24ca8c9aa06c-0-1400x919.jpg",
    "taste key": "011100",
    "tags": []
    },
    {
        "location": "https://upload.wikimedia.org/wikipedia/commons/a/a3/Eq_it-na_pizza-margherita_sep2005_sml.jpg",
        "taste key": "011100",
        "tags": []
    },
    {
        "location": "https://external-content.duckduckgo.com/iu/?u=https%3A%2F%2Fthumbs-prod.si-cdn.com%2Fv_0qISgeD3e1T64-vmRUFwZG2jA%3D%2F800x600%2Ffilters%3Ano_upscale()%2Fhttps%3A%2F%2Fpublic-media.si-cdn.com%2Ffiler%2F93%2F6d%2F936d3e1c-9ba0-4251-bbfc-83f7edd3968f%2Fistock-173802143.jpg&f=1&nofb=1",
        "taste key": "011100",
        "tags": []
    },
    {
        "location": "https://external-content.duckduckgo.com/iu/?u=https%3A%2F%2Fpenzit.com%2Fwp-content%2Fuploads%2F2020%2F07%2FChicken-Bitter-Melon-Gourd.jpg&f=1&nofb=1",
        "taste key": "011100",
        "tags": []
    },
    {
        "location": "https://www.japan.go.jp/kizuna/_src/7989285/sushi_robots_01.jpg?v=1646641593194",
        "taste key": "011100",
        "tags": []
    },
    {
        "location": "https://external-content.duckduckgo.com/iu/?u=http%3A%2F%2Fwww.indigofinance.com.au%2Fwp-content%2Fuploads%2F2018%2F07%2Fistock-157528129.jpg&f=1&nofb=1",
        "taste key": "011100",
        "tags": []
    },
    {
        "location": "https://external-content.duckduckgo.com/iu/?u=https%3A%2F%2Fi1.wp.com%2Feuroviajar.com%2Fwp-content%2Fuploads%2F2019%2F12%2FAnother-typical-Greek-food-Souvlaki-brochette-of-meat-skewers.jpg%3Fw%3D2000%26ssl%3D1&f=1&nofb=1",
        "taste key": "011100",
        "tags": []
    },
    {
        "location": "https://external-content.duckduckgo.com/iu/?u=https%3A%2F%2Fi.pinimg.com%2Foriginals%2Fa5%2Fd5%2Fe2%2Fa5d5e2173cbcc0e631855e2d9aa77a7a.jpg&f=1&nofb=1",
        "taste key": "011100",
        "tags": []
    }
]



